logcontrol/__init__.py
logcontrol/constants.py
logcontrol/loggers.py
logcontrol/validation.py
logcontrol-0.2.1.dist-info/COPYING
logcontrol-0.2.1.dist-info/COPYING.LESSER
logcontrol-0.2.1.dist-info/LICENSE
logcontrol-0.2.1.dist-info/METADATA
logcontrol-0.2.1.dist-info/WHEEL
logcontrol-0.2.1.dist-info/top_level.txt
logcontrol-0.2.1.dist-info/RECORD
