Metadata-Version: 2.1
Name: logcontrol
Version: 0.2.1
Summary: A logger manager for Python programs
Home-page: https://github.com/brandonmpace/logcontrol
Author: Brandon M. Pace
Author-email: brandonmpace@gmail.com
License: GNU Lesser General Public License v3 or later
Keywords: debug log logging logger level control manager
Platform: any
Classifier: Development Status :: 5 - Production/Stable
Classifier: License :: OSI Approved :: GNU Lesser General Public License v3 or later (LGPLv3+)
Classifier: Operating System :: OS Independent
Classifier: Programming Language :: Python :: 3
Requires-Python: >=3.6.5
